sql_utils/README.md
sql_utils/__init__.py
sql_utils/dbpools_util.py
sql_utils/mdb_util.py
sql_utils/mysql_operation.py
sql_utils/postgressql_util.py
sql_utils/pymssql_util.py
sql_utils/pyodbc_util.py
sql_utils/sqlalchemy_util.py
sql_utils/sqlite_operation.py
sql_utils/tinydb_util.py
allsql_utils-0.0.4.dist-info/LICENSE
allsql_utils-0.0.4.dist-info/METADATA
allsql_utils-0.0.4.dist-info/WHEEL
allsql_utils-0.0.4.dist-info/top_level.txt
allsql_utils-0.0.4.dist-info/RECORD
