Metadata-Version: 2.1
Name: allsql-utils
Version: 0.0.4
Summary: Short description
Home-page: https://gitee.com/SkyOceanchen/sql_utils.git
Author: SkyOceanChen
Author-email: skyoceanchen@foxmail.com
Maintainer: SkyOceanChen
Maintainer-email: skyoceanchen@foxmail.com
License: MIT
Classifier: Development Status :: 3 - Alpha
Classifier: Intended Audience :: Developers
Classifier: Operating System :: OS Independent
Classifier: Topic :: Software Development :: Build Tools
Classifier: License :: OSI Approved :: MIT License
Classifier: Programming Language :: Python :: 3.6
Classifier: Programming Language :: Python :: 3.8
Classifier: Programming Language :: Python :: 3.10
Requires-Python: ~=3.3
License-File: LICENSE
Requires-Dist: pymysql (==1.1.0)
Requires-Dist: psycopg2 (==2.9.7)
Requires-Dist: pymssql (==2.2.8)
Requires-Dist: pyodbc (==4.0.39)
Requires-Dist: SQLAlchemy (==2.0.19)
Requires-Dist: tinydb (==4.8.0)
Requires-Dist: DBUtils (==3.1.0)
